suxiawei01/__init__.py
suxiawei01/first.py
suxiawei01/second.py
suxiawei01/copy/__init__.py
suxiawei01/copy/third.py
suxiawei01-0.0.1.dist-info/LICENSE
suxiawei01-0.0.1.dist-info/METADATA
suxiawei01-0.0.1.dist-info/WHEEL
suxiawei01-0.0.1.dist-info/top_level.txt
suxiawei01-0.0.1.dist-info/RECORD
