Metadata-Version: 2.1
Name: suxiawei01
Version: 0.0.1
Summary: just test
Home-page: https://www.baidu.com/
Author: suxiawei
Author-email: 773979910@qq.com
License: UNKNOWN
Platform: UNKNOWN
Classifier: Programming Language :: Python :: 3
Classifier: License :: OSI Approved :: MIT License
Classifier: Operating System :: OS Independent
Requires-Dist: pandas
